<?xml version="1.0" encoding="UTF-8" ?>

<routes xmlns="http://symfony.com/schema/routing"
    xmlns:xsi="http://www.w3.org/2001/XMLSchema-instance"
    xsi:schemaLocation="http://symfony.com/schema/routing http://symfony.com/schema/routing/routing-1.0.xsd">

    <route id="blueonrailsblockinn_oauth_homepage" pattern="/oauth/v2/auth_login">
        <default key="_controller">blueonrailsblockinnOauthBundle:Security:login</default>
    </route>
    
    <route id="blueonrailsblockinn_oauth_homepage" pattern="/oauth/v2/auth_login_check">
        <default key="_controller">blueonrailsblockinnOauthBundle:Security:loginCheck</default>
    </route>
    
</routes>
